efficiency/__init__.py
efficiency/bib.py
efficiency/file_manager.py
efficiency/function.py
efficiency/log.py
efficiency/nlp.py
efficiency/plotter.py
efficiency/record.py
efficiency/text.py
efficiency/web.py
efficiency/mt/__init__.py
efficiency/mt/loss_plot.py
efficiency/mt/tensorboard_logging.py
efficiency-1.31.dist-info/LICENSE.txt
efficiency-1.31.dist-info/METADATA
efficiency-1.31.dist-info/WHEEL
efficiency-1.31.dist-info/top_level.txt
efficiency-1.31.dist-info/RECORD
