Metadata-Version: 2.1
Name: efficiency
Version: 1.31
Summary: A package for efficient programming
Home-page: https://github.com/zhijing-jin/efficiency
Author: Zhijing Jin
License: MIT
License-File: LICENSE.txt
